buildbot_tag_filters_plugin/VERSION
buildbot_tag_filters_plugin/__init__.py
buildbot_tag_filters_plugin/static/scripts.js
buildbot_tag_filters_plugin-2024.8.8.dist-info/METADATA
buildbot_tag_filters_plugin-2024.8.8.dist-info/WHEEL
buildbot_tag_filters_plugin-2024.8.8.dist-info/entry_points.txt
buildbot_tag_filters_plugin-2024.8.8.dist-info/top_level.txt
buildbot_tag_filters_plugin-2024.8.8.dist-info/RECORD
