Metadata-Version: 2.1
Name: buildbot-tag-filters-plugin
Version: 2024.8.8
Summary: Add builders filters menu section
Home-page: https://github.com/pp1e
Author: Denis Malyutin
Author-email: denis.malyutin@fruct.org
Classifier: License :: OSI Approved :: GNU General Public License v2 (GPLv2)
